littledoc/__init__.py
littledoc/main.py
littledoc/parser.py
littledoc/writer.py
littledoc-0.0.2.dist-info/LICENSE
littledoc-0.0.2.dist-info/METADATA
littledoc-0.0.2.dist-info/WHEEL
littledoc-0.0.2.dist-info/dependency_links.txt
littledoc-0.0.2.dist-info/entry_points.txt
littledoc-0.0.2.dist-info/top_level.txt
littledoc-0.0.2.dist-info/RECORD
