Metadata-Version: 2.1
Name: littledoc
Version: 0.0.2
Summary: A small Python code parser which allow to generate a basic documentation
Home-page: https://github.com/jpthiery/littledoc
Author: Jean-Pascal Thiery
License: Apache Software License (http://www.apache.org/licenses/LICENSE-2.0)
Keywords: documentation
Platform: UNKNOWN
Classifier: License :: OSI Approved :: Apache Software License
Classifier: Programming Language :: Python :: 3
Classifier: Programming Language :: Python :: 3.9
Classifier: Operating System :: OS Independent
Requires-Python: >=3
License-File: LICENSE
Requires-Dist: argparse (==1.4.0)
Requires-Dist: jinja2 (==3.0.1)
